<?xml version="1.0"?>
<!DOCTYPE hibernate-mapping PUBLIC "-//Hibernate/Hibernate Mapping DTD 3.0//EN"
"http://hibernate.sourceforge.net/hibernate-mapping-3.0.dtd">
<!-- Generated 1 ???????? 2011 9:38:45 by Hibernate Tools 3.3.0.GA -->
<hibernate-mapping>

<class name="net.it_tim.security_console.Camera" table="camera">
		<id name="id" type="java.lang.Long">
			<column name="id" not-null="true" unique="true" />
			<generator class="increment"></generator>
		</id>
		<property name="description" type="java.lang.String">
			<column name="description" length="65" />
		</property>
		<property name="camera_url" type="java.lang.String"	access="field">
			<column name="camera_url" length="150" />
		</property>
	</class>
</hibernate-mapping>
